{
  "resourceType": "Immunization",
  "id": "644253",
  "meta": {
    "versionId": "1",
    "lastUpdated": "2020-03-20T21:12:58.361+00:00",
    "source": "#c5qCrD7M8OaTm5Jc"
  },
  "status": "completed",
  "vaccineCode": {
    "coding": [
      {
        "system": "http://hl7.org/fhir/sid/cvx",
        "code": "85"
      }
    ],
    "text": "Hep A unspecified formulation"
  },
  "patient": {
    "reference": "Patient/1100"
  },
  "occurrenceDateTime": "2020-02-06",
  "reasonCode": [
    {
      "text": "Evaluation_Status_2.0: Not Valid\nEvaluation_Reason_2.0: Interval: too short"
    }
  ]
}